CampbellSCIParser-0.38b0.dist-info/DESCRIPTION.rst
CampbellSCIParser-0.38b0.dist-info/METADATA
CampbellSCIParser-0.38b0.dist-info/RECORD
CampbellSCIParser-0.38b0.dist-info/WHEEL
CampbellSCIParser-0.38b0.dist-info/metadata.json
CampbellSCIParser-0.38b0.dist-info/top_level.txt
campbellsciparser/__init__.py
campbellsciparser/cr.py
campbellsciparser/dataset.py
campbellsciparser/devices/__init__.py
campbellsciparser/devices/base.py
campbellsciparser/devices/common.py
campbellsciparser/devices/cr10.py
campbellsciparser/devices/cr1000.py
campbellsciparser/devices/cr10x.py
