Metadata-Version: 2.0
Name: CampbellSCIParser
Version: 0.38b0
Summary: Parser for Campbell Scientific dataloggers
Home-page: https://github.com/SunBurst/campbellsciparser
Author: Marcus Enderskog
Author-email: marcus.enderskog@gmail.com
License: MIT
Platform: UNKNOWN
Classifier: Development Status :: 4 - Beta
Classifier: Intended Audience :: Science/Research
Classifier: Intended Audience :: Developers
Classifier: Topic :: Utilities
Classifier: Topic :: Software Development :: Libraries :: Python Modules
Classifier: License :: OSI Approved :: MIT License
Classifier: Programming Language :: Python :: 3
Classifier: Programming Language :: Python :: 3.3
Classifier: Programming Language :: Python :: 3.4
Classifier: Programming Language :: Python :: 3.5
Requires-Dist: pytz
